icsdll/__init__.py
icsdll/icsdll.py
icsdll-2025.8.8.dist-info/licenses/LICENSE
icsdll-2025.8.8.dist-info/METADATA
icsdll-2025.8.8.dist-info/WHEEL
icsdll-2025.8.8.dist-info/top_level.txt
icsdll-2025.8.8.dist-info/RECORD
